transkription_vosk/__init__.py
transkription_vosk/transkription_vosk.py
transkription_vosk-0.1.2.dist-info/LICENSE
transkription_vosk-0.1.2.dist-info/METADATA
transkription_vosk-0.1.2.dist-info/WHEEL
transkription_vosk-0.1.2.dist-info/entry_points.txt
transkription_vosk-0.1.2.dist-info/top_level.txt
transkription_vosk-0.1.2.dist-info/RECORD
