Metadata-Version: 2.1
Name: transkription-vosk
Version: 0.1.2
Summary: Ein Paket zur Transkription von Audiodateien mit Vosk-Modellen, lokal auf dem Rechner.
Home-page: https://github.com/martialjob/transkription_vosk
Author: Martial Job
Author-email: transkription_vosk@mjob.me
License: UNKNOWN
Platform: UNKNOWN
Classifier: Programming Language :: Python :: 3
Classifier: License :: OSI Approved :: MIT License
Classifier: Operating System :: OS Independent
Requires-Python: >=3.6
Requires-Dist: vosk
Requires-Dist: pydub
